scutum/__init__.py
scutum/authorizable.py
scutum/cache.py
scutum/exceptions.py
scutum/gate.py
scutum/policy.py
scutum/response.py
scutum/scope.py
scutum/types.py
scutum/ext/__init__.py
scutum/ext/fastapi.py
scutum/ext/flask.py
scutum-0.2.0.dist-info/METADATA
scutum-0.2.0.dist-info/WHEEL
scutum-0.2.0.dist-info/RECORD
