Metadata-Version: 2.4
Name: scutum
Version: 0.2.0
Summary: Framework-agnostic authorization gates inspired by Laravel
Project-URL: Homepage, https://github.com/jigordev/scutum
Project-URL: Repository, https://github.com/jigordev/scutum
Project-URL: Issues, https://github.com/jigordev/scutum/issues
Project-URL: Documentation, https://github.com/jigordev/scutum#readme
Author-email: "J. Igor Melo" <jigordev@gmail.com>
License: MIT
Keywords: acl,authorization,fastapi,flask,permissions,rbac
Classifier: Development Status :: 3 - Alpha
Classifier: Framework :: Django
Classifier: Framework :: FastAPI
Classifier: Framework :: Flask
Classifier: Intended Audience :: Developers
Classifier: License :: OSI Approved :: MIT License
Classifier: Programming Language :: Python :: 3
Requires-Python: >=3.10
Provides-Extra: flask
Requires-Dist: flask>=2.0.0; extra == 'flask'
